flake8_ruff/__init__.py
flake8_ruff/py.typed
flake8_ruff-0.3.1.dist-info/METADATA
flake8_ruff-0.3.1.dist-info/WHEEL
flake8_ruff-0.3.1.dist-info/entry_points.txt
flake8_ruff-0.3.1.dist-info/licenses/LICENCE
flake8_ruff-0.3.1.dist-info/RECORD
