Metadata-Version: 2.4
Name: flake8-ruff
Version: 0.3.1
Summary: A Flake8 plugin that implements miscellaneous checks from Ruff.
Project-URL: Repository, https://github.com/tjkuson/flake8-ruff
Author-email: Tom Kuson <mail@tjkuson.me>
License-Expression: MIT
License-File: LICENCE
Keywords: flake8,ruff
Classifier: Development Status :: 4 - Beta
Classifier: Framework :: Flake8
Classifier: Intended Audience :: Developers
Classifier: License :: OSI Approved :: MIT License
Classifier: Natural Language :: English
Classifier: Programming Language :: Python :: 3 :: Only
Classifier: Programming Language :: Python :: 3.9
Classifier: Programming Language :: Python :: 3.10
Classifier: Programming Language :: Python :: 3.11
Classifier: Programming Language :: Python :: 3.12
Classifier: Programming Language :: Python :: 3.13
Classifier: Typing :: Typed
Requires-Python: >=3.9
